{
  "patient": {
    "external_id": "P001",
    "name": "Test Patient",
    "sex": "F",
    "dob": "1985-01-01"
  },
  "report_date": "2025-11-01",
  "tests": [
    {
      "code": "HGB",
      "name": "Hemoglobin",
      "value": 10.5,
      "unit": "g/dL",
      "normal_range_low": 12.0,
      "normal_range_high": 15.5,
      "flag": "Low"
    },
    {
      "code": "TSH",
      "name": "Thyroid Stimulating Hormone (TSH)",
      "value": 3.2,
      "unit": "µIU/mL",
      "normal_range_low": 0.4,
      "normal_range_high": 4.0,
      "flag": "Normal"
    }
  ]
}
